argparse_from_file/__init__.py
argparse_from_file/argparse.py
argparse_from_file/py.typed
argparse_from_file-1.7.dist-info/METADATA
argparse_from_file-1.7.dist-info/WHEEL
argparse_from_file-1.7.dist-info/top_level.txt
argparse_from_file-1.7.dist-info/RECORD
