Metadata-Version: 2.4
Name: argparse-from-file
Version: 1.7
Summary: Wrapper for Python's argparse to also read arguments from a file
Author-email: Mark Blakeney <mark.blakeney@bullet-systems.net>
License-Expression: GPL-3.0-or-later
Project-URL: Homepage, https://github.com/bulletmark/argparse-from-file
Keywords: argparse,ConfigArgParse
Classifier: Programming Language :: Python :: 3
Requires-Python: >=3.8
Requires-Dist: platformdirs
